pyqt_textbox_graphics_widget/__init__.py
pyqt_textbox_graphics_widget/textBoxBrowser.py
pyqt_textbox_graphics_widget/textBoxGraphicsWidget.py
pyqt_textbox_graphics_widget-0.0.1.dist-info/LICENSE
pyqt_textbox_graphics_widget-0.0.1.dist-info/METADATA
pyqt_textbox_graphics_widget-0.0.1.dist-info/WHEEL
pyqt_textbox_graphics_widget-0.0.1.dist-info/top_level.txt
pyqt_textbox_graphics_widget-0.0.1.dist-info/RECORD
