Metadata-Version: 2.1
Name: pyqt-textbox-graphics-widget
Version: 0.0.1
Summary: PyQt text box which is movable, auto-resizable by text size. Parent class is QGraphicsWidget.
Home-page: https://github.com/yjg30737/pyqt-textbox-graphics-widget.git
Author: Jung Gyu Yoon
Author-email: yjg30737@gmail.com
License: MIT
Platform: UNKNOWN
License-File: LICENSE
Requires-Dist: PyQt5 (>=5.8)
